advanced_decorators/__init__.py
advanced_decorators/advanced_decorators.py
basic_decorators/__init__.py
basic_decorators/basic_decorators.py
decorator_collection-1.0.0.dist-info/METADATA
decorator_collection-1.0.0.dist-info/WHEEL
decorator_collection-1.0.0.dist-info/top_level.txt
decorator_collection-1.0.0.dist-info/RECORD
