Metadata-Version: 2.1
Name: decorator-collection
Version: 1.0.0
Summary: A collection of basic and advanced Python decorators
Author: Aiden Metcalfe
Author-email: avaartshop@outlook.com
Classifier: Programming Language :: Python :: 3
Classifier: License :: OSI Approved :: MIT License
Classifier: Operating System :: OS Independent
Requires-Python: >=3.11
Requires-Dist: jsonschema
